README.md
setup.py
yacho/__init__.py
yacho/__main__.py
yacho/build.py
yacho/cli.py
yacho/config.py
yacho/sketch_generator.py
yacho.egg-info/PKG-INFO
yacho.egg-info/SOURCES.txt
yacho.egg-info/dependency_links.txt
yacho.egg-info/entry_points.txt
yacho.egg-info/requires.txt
yacho.egg-info/top_level.txt