Metadata-Version: 2.1
Name: yacho
Version: 0.0.2.1
Summary: yacho
Home-page: https://github.com/eqs/yacho
Author: eqs
Author-email: murashige.satoshi.mi1@gmail.com
License: MIT
Platform: UNKNOWN
Classifier: Development Status :: 2 - Pre-Alpha
Classifier: License :: OSI Approved :: MIT License
Classifier: Programming Language :: Python
Classifier: Programming Language :: Python :: 3.7
Classifier: Programming Language :: Python :: 3.8
Classifier: Programming Language :: Python :: 3.9
